tc_http_loader_prefix/__init__.py
tc_http_loader_prefix/config.py
tc_http_loader_prefix/loader.py
tc_http_loader_prefix-0.1.4.dist-info/licenses/LICENSE
tests/test_loader.py
tc_http_loader_prefix-0.1.4.dist-info/METADATA
tc_http_loader_prefix-0.1.4.dist-info/WHEEL
tc_http_loader_prefix-0.1.4.dist-info/entry_points.txt
tc_http_loader_prefix-0.1.4.dist-info/top_level.txt
tc_http_loader_prefix-0.1.4.dist-info/RECORD
