Metadata-Version: 2.4
Name: tc_http_loader_prefix
Version: 0.1.4
Summary: A small package to provide a predefined base host for HTTP loader
License: MIT
Project-URL: Homepage, https://github.com/jcord04/thumbor-http-load-prefix
Project-URL: Issues, https://github.com/jcord04/thumbor-http-load-prefix/issues
Classifier: Programming Language :: Python :: 3
Classifier: Operating System :: OS Independent
Requires-Python: >=3.8
License-File: LICENSE
Requires-Dist: thumbor
Provides-Extra: dev
Requires-Dist: pytest; extra == "dev"
Dynamic: license-file
